Workbook

Sheet Dashboard
A1: INDIVIDUAL GIVING & DONOR CULTIVATION TOOLKIT
A2: Module 2: Individual Giving & Donor Relations | Build Your Club Nonprofit Fundraising Course
A4: ORGANIZATION INFORMATION
A5: Organization Name: | D5: Fiscal Year:
A6: Development Officer: | D6: Date Updated:
A8: DONOR PIPELINE STAGE SUMMARY
A9: ℹ Update the Donor Pipeline sheet to populate summary counts below. Counts pull from column C of that sheet.
A10: Lifecycle Stage | B10: # of Prospects/Donors | C10: % of Pipeline | D10: Proposed Ask Total ($) | E10: Avg. Proposed Ask ($) | F10: Notes
A11: Identified | B11: =COUNTIF('Donor Pipeline'!C:C,"Identified") -> 1 | C11: =IF(B11+B17=0,"-",B11/B17) -> 0.2 | D11: =SUMIF('Donor Pipeline'!C:C,"Identified",'Donor Pipeline'!I:I) -> 0 | E11: =IF(B11=0,"-",D11/B11) -> 0 | F11: Initial list — not yet contacted
A12: Qualified | B12: =COUNTIF('Donor Pipeline'!C:C,"Qualified") -> 1 | C12: =IF(B12+B17=0,"-",B12/B17) -> 0.2 | D12: =SUMIF('Donor Pipeline'!C:C,"Qualified",'Donor Pipeline'!I:I) -> 0 | E12: =IF(B12=0,"-",D12/B12) -> 0 | F12: Three Cs confirmed
A13: In Cultivation | B13: =COUNTIF('Donor Pipeline'!C:C,"In Cultivation") -> 1 | C13: =IF(B13+B17=0,"-",B13/B17) -> 0.2 | D13: =SUMIF('Donor Pipeline'!C:C,"In Cultivation",'Donor Pipeline'!I:I) -> 2500 | E13: =IF(B13=0,"-",D13/B13) -> 2500 | F13: Actively building relationship
A14: Recently Solicited | B14: =COUNTIF('Donor Pipeline'!C:C,"Recently Solicited") -> 0 | C14: =IF(B14+B17=0,"-",B14/B17) -> 0 | D14: =SUMIF('Donor Pipeline'!C:C,"Recently Solicited",'Donor Pipeline'!I:I) -> 0 | E14: =IF(B14=0,"-",D14/B14) -> - | F14: Ask made; awaiting response
A15: In Stewardship | B15: =COUNTIF('Donor Pipeline'!C:C,"In Stewardship") -> 1 | C15: =IF(B15+B17=0,"-",B15/B17) -> 0.2 | D15: =SUMIF('Donor Pipeline'!C:C,"In Stewardship",'Donor Pipeline'!I:I) -> 10000 | E15: =IF(B15=0,"-",D15/B15) -> 10000 | F15: Gift received; nurturing for renewal
A16: Lapsed | B16: =COUNTIF('Donor Pipeline'!C:C,"Lapsed") -> 1 | C16: =IF(B16+B17=0,"-",B16/B17) -> 0.2 | D16: =SUMIF('Donor Pipeline'!C:C,"Lapsed",'Donor Pipeline'!I:I) -> 1000 | E16: =IF(B16=0,"-",D16/B16) -> 1000 | F16: Prior donor; no gift in 12+ months
A17: TOTAL PIPELINE | B17: =SUM(B11:B16) -> 5 | C17: 100% | D17: =SUM(D11:D16) -> 13500 | E17: =IF(B17=0,"-",D17/B17) -> 2700
A19: KEY PERFORMANCE INDICATORS
A20: KPI | B20: Current Value | C20: Target | D20: Status | E20: Formula / Notes
A21: Donor Retention Rate | C21: 50%+ | E21: # Donors who gave again ÷ Total donors from prior year
A22: First-Time Donor Retention | C22: 30%+ | E22: First-time donors renewed ÷ Total first-time donors (prior year)
A23: Donor Upgrade Rate | C23: 25%+ | E23: # Donors who increased gift ÷ Total renewed donors
A24: Pipeline Conversion Rate | C24: 20%+ | E24: Prospects solicited ÷ Total prospects in cultivation
A25: Average Gift Size | E25: Total individual giving revenue ÷ # of gifts
A26: Total Individual Giving Revenue ($) | E26: Sum of all individual gifts received this year
A27: # Active Major Gift Prospects | B27: =COUNTIF('Donor Pipeline'!C:C,"In Cultivation") -> 1 | C27: 30–50 | E27: Prospects in active cultivation stage
A28: Touches per Major Donor per Year | C28: 7–10 | E28: # of meaningful touchpoints per major donor
A30: STATUS LEGEND
A31: ✅ On Track | B31: ⚠️ Needs Attention | C31: ❌ Off Track | D31: 📋 Not Yet Tracked
A33: 💡 TIP: Enter your KPI values manually in column B, or link them from the tracker sheets. Update monthly for best insights.

Sheet Donor Pipeline
A1: DONOR PIPELINE — PROSPECT & DONOR MASTER TRACKER
A2: Module 2: Individual Giving & Donor Relations | Track every prospect and donor through the full lifecycle
A3: ℹ INSTRUCTIONS: Add every prospect and donor here. Update Lifecycle Stage, Three Cs scores, and Last Contact after every meaningful interaction. Use this as your master pipeline view.
A4: ID / NAME | C4: LIFECYCLE STAGE & THREE Cs QUALIFICATION | G4: GIFT INTELLIGENCE | K4: CONTACT TRACKING | M4: PORTFOLIO MANAGEMENT
A5: # | B5: Prospect / Donor Name | C5: Lifecycle Stage | D5: Capacity (H/M/L) | E5: Connection (H/M/L) | F5: Concern (H/M/L) | G5: Proposed Ask ($) | H5: Gift Purpose / Program | I5: Largest Prior Gift ($) | J5: Total Lifetime Giving ($) | K5: Last Contact Date | L5: Next Action Date | M5: Assigned To | N5: Notes / Next Move
A6: 1 | B6: Maria Johnson | C6: In Cultivation | D6: H | E6: H | F6: H | G6: 25000 | H6: Youth Education Fund | I6: 2500 | J6: 7500 | K6: 04/15/2026 | L6: 05/20/2026 | M6: Development Director | N6: Board referral; excited about mentorship program. Schedule site visit.
A7: 2 | B7: Robert & Susan Chen | C7: In Stewardship | D7: H | E7: M | F7: H | G7: 50000 | H7: Scholarship Endowment | I7: 10000 | J7: 28000 | K7: 04/28/2026 | L7: 06/10/2026 | M7: Executive Director | N7: Gave $10K in March. Send impact report by June. Renewal convo in Q4.
A8: 3 | B8: David Martinez | C8: Qualified | D8: M | E8: H | F8: H | G8: 5000 | H8: General Operations | I8: 0 | J8: 0 | K8: 05/01/2026 | L8: 05/15/2026 | M8: Development Director | N8: Long-time volunteer; never asked. Book discovery lunch.
A9: 4 | B9: Patricia Williams | C9: Identified | D9: H | E9: L | F9: M | G9: 15000 | H9: Capital Campaign | I9: 0 | J9: 0 | L9: 05/30/2026 | M9: Board Member A | N9: Community philanthropist. Need warm intro from board.
A10: 5 | B10: James Thompson | C10: Lapsed | D10: M | E10: H | F10: H | G10: 2500 | H10: Annual Fund | I10: 1000 | J10: 3000 | K10: 01/10/2026 | L10: 05/20/2026 | M10: Development Director | N10: Gave 3 yrs in a row, lapsed in 2025. Send personal re-engagement letter.
A57: LIFECYCLE STAGE KEY
A58: Identified | B58: Prospect found; no meaningful contact yet
A59: Qualified | B59: Three Cs confirmed; ready for active cultivation
A60: In Cultivation | B60: Actively building relationship with planned moves
A61: Recently Solicited | B61: Ask made; awaiting or following up on response
A62: In Stewardship | B62: Gift received; executing stewardship plan for renewal
A63: Lapsed | B63: Prior donor; no gift in 12+ months; re-engagement needed

Sheet Moves Management Log
A1: MOVES MANAGEMENT LOG — CULTIVATION TOUCHPOINT TRACKER
A2: Module 2: Individual Giving & Donor Relations | Track every meaningful interaction with major gift prospects
A3: ℹ INSTRUCTIONS: Log every significant cultivation touchpoint immediately after it occurs. A 'move' is any intentional interaction designed to deepen the prospect's relationship with your organization. Update Next Move and Date after each entry.
A4: # | B4: Prospect / Donor Name | C4: Date | D4: Touchpoint Type | E4: Attended By (Staff/Board) | F4: What Was Discussed / Accomplished | G4: What Was Learned (Interests, Concerns) | H4: Next Planned Move | I4: Next Move Target Date | J4: Lifecycle Stage after Move
A5: 1 | B5: Maria Johnson | C5: 03/12/2026 | D5: Discovery Meeting | E5: Dev. Director | F5: One-on-one coffee. Shared overview of mentorship program outcomes. | G5: Passionate about youth; wants impact data on job placements post-program. | H5: Site visit with program director to meet a mentee | I5: 04/15/2026 | J5: In Cultivation
A6: 2 | B6: Maria Johnson | C6: 04/15/2026 | D6: Site Visit / Tour | E6: Dev. Director + Program Director | F6: Toured facility; Maria met two mentees and heard their stories directly. | G6: Moved to tears during mentee presentations. 'This is exactly what I care about.' | H6: Personal thank-you call from ED + invite to spring board breakfast | I6: 04/20/2026 | J6: In Cultivation
A7: 3 | B7: Robert & Susan Chen | C7: 03/28/2026 | D7: Board Member Lunch | E7: Board Chair + ED | F7: Lunch with Board Chair. Discussed scholarship program and endowment opportunity. | G7: Interested in legacy giving; wants scholarship named for their late son. | H7: Send named scholarship proposal; schedule follow-up call | I7: 04/10/2026 | J7: Recently Solicited
A8: 4 | B8: David Martinez | C8: 05/01/2026 | D8: Discovery Meeting | E8: Dev. Director | F8: Lunch at local restaurant. First formal conversation about philanthropy. | G8: Deeply loyal volunteer; never considered a major gift. Open to the idea. | H8: Follow up with personal note + invite to next cultivation event | I8: 05/15/2026 | J8: Qualified
A9: 5 | B9: James Thompson | C9: 05/05/2026 | D9: Phone Check-In | E9: Dev. Director | F9: Re-engagement call after 18 months of lapse. Warm response. | G9: Had a difficult personal year; still cares about the mission. | H9: Send personalized impact report showing 2025 program outcomes | I9: 05/12/2026 | J9: In Cultivation
A61: TOUCHPOINT TYPE REFERENCE
A62: Discovery Meeting | B62: One-on-one conversation focused on learning about the prospect's values and interests. No ask.
A63: Site Visit / Tour | B63: Bring prospect to see your work firsthand. Most powerful cultivation tool.
A64: Program Introduction | B64: Introduce prospect to program staff or beneficiaries (with consent).
A65: Event Invitation | B65: Cultivation breakfast, donor circle, behind-the-scenes gathering.
A66: Impact Update | B66: Personalized story or outcome report — NOT a newsletter. Personal and specific.
A67: Board Member Engagement | B67: Personal call, note, or lunch from a board member who shares the prospect's background.
A68: Handwritten Note | B68: Brief personal note after an event, announcement, or milestone in prospect's life.
A69: Phone Check-In | B69: Brief call to stay connected, share news, or follow up on a previous conversation.
A70: Volunteer Opportunity | B70: Offer a meaningful volunteer role before making a financial ask.

Sheet Solicitation Tracker
A1: SOLICITATION TRACKER — ASK LOG & OUTCOMES
A2: Module 2: Individual Giving & Donor Relations | Track every solicitation from ask through outcome and next steps
A3: ℹ INSTRUCTIONS: Log every formal solicitation (ask). Record the date, method, amount asked, response, actual gift, and follow-up plan. Use the Response column to track where each ask stands. Update as outcomes become known.
A4: # | B4: Prospect / Donor Name | C4: Ask Date | D4: Solicitation Method | E4: Amount Asked ($) | F4: Gift Purpose / Program | G4: Response | H4: Actual Gift Received ($) | I4: Follow-Up Deadline | J4: Next Steps / Notes
A5: SUMMARY (auto-calculated from rows below)
A6: Total Asks Made: | B6: =COUNTA(C7:C106)-COUNTBLANK(C7:C106) -> -92 | C6: Total Pledged / Received ($): | D6: =SUM(H7:H106) -> 10000 | E6: Success Rate: | F6: =IF(COUNTA(C7:C106)-COUNTBLANK(C7:C106)=0,"-",COUNTIF(G7:G106,"Yes - Gift Received")/(COUNTA(C7:C106)-COUNTBLANK(C7:C106))) -> -0.010869565 | G6: Avg. Gift Received ($): | H6: =IF(COUNTIF(G7:G106,"Yes - Gift Received")=0,"-",SUMIF(G7:G106,"Yes - Gift Received",H7:H106)/COUNTIF(G7:G106,"Yes - Gift Received")) -> 10000 | I6: Asks Pending Response: | J6: =COUNTIF(G7:G106,"Pending") -> 1
A7: 1 | B7: Robert & Susan Chen | C7: 04/12/2026 | D7: Face-to-Face | E7: 50000 | F7: Named Scholarship | G7: Thinking It Over | H7: 0 | I7: 04/28/2026 | J7: Meeting with spouse on 4/25. Follow up 4/28 with named gift proposal.
A8: 2 | B8: Maria Johnson | C8: 05/20/2026 | D8: Face-to-Face | E8: 25000 | F8: Youth Education Fund | G8: Pending | H8: 0 | I8: 06/05/2026 | J8: Asked at cultivation dinner. Awaiting response.
A9: 3 | B9: Patricia Williams | C9: 03/05/2026 | D9: Phone | E9: 15000 | F9: Capital Campaign | G9: Yes - Gift Received | H9: 10000 | J9: Accepted at lower amount ($10K). Send acknowledgment and tour invite.
A10: 4 | B10: James Thompson | C10: 05/15/2026 | D10: Phone | E10: 2500 | F10: Annual Fund | G10: No - Declined (this cycle) | H10: 0 | I10: 11/01/2026 | J10: Said 'not this year.' Re-solicit in fall. Continue stewardship.
A108: RESPONSE OPTIONS REFERENCE
A109: Yes - Gift Received | B109: Donor committed and gift has been received. Begin immediate stewardship.
A110: Pledge Received | B110: Donor committed to a pledge payable over time. Document pledge schedule.
A111: Thinking It Over | B111: Donor needs more time. Agree on specific follow-up date. Ask what would help.
A112: Pending | B112: Ask made; awaiting initial response. Follow up within agreed timeframe.
A113: No - Declined (this cycle) | B113: Declined this ask. Note reason if known. Continue stewardship; re-solicit in 12 months.

Sheet Stewardship Calendar
A1: DONOR STEWARDSHIP CALENDAR — ANNUAL TOUCHPOINT PLAN
A2: Module 2: Individual Giving & Donor Relations | Plan 7–10 meaningful touchpoints per major donor per year
A3: ℹ INSTRUCTIONS: List each donor in column A. For each month, enter the planned touchpoint type (or 'Done ✓' when completed). Aim for 7–10 meaningful touches per year for major donors. Use the Touchpoint Key below.
A4: Donor Name | B4: Level | C4: Jan | D4: Feb | E4: Mar | F4: Apr | G4: May | H4: Jun | I4: Jul | J4: Aug | K4: Sep | L4: Oct | M4: Nov | N4: Dec | O4: Notes / Stewardship Priority
A5: Robert & Susan Chen | B5: Major | C5: Thank-You Call | D5: Impact Update | F5: Event Invite | H5: Mid-Year Report | J5: Personal Note | K5: Annual Report | M5: Renewal Cultivation | N5: Renewal Solicitation | O5: Named scholarship ask in progress. 7-touch minimum.
A6: Maria Johnson | B6: Major | C6: Discovery Mtg | E6: Site Visit | G6: Board Breakfast | I6: Impact Update | K6: Event Invite | M6: Renewal Cultivation | N6: Solicitation | O6: Active cultivation. Target: $25K ask in May.
A7: Patricia Williams | B7: Mid-Level | C7: Thank-You Call | E7: Impact Update | G7: Event Invite | I7: Mid-Year Report | L7: Renewal Cultivation | N7: Renewal Solicitation | O7: First gift received March 2026.
A8: David Martinez | B8: Mid-Level | G8: Discovery Lunch | I8: Impact Update | K8: Event Invite | M8: Cultivation Call | N8: Solicitation? | O8: Long-time volunteer; moving toward first major ask.
A9: James Thompson | B9: Annual | C9: Re-engage Call | E9: Impact Report | H9: Phone Check-In | K9: Annual Report | M9: Renewal Solicitation | O9: Lapsed donor; reactivation underway.
A10: Susan Park | B10: Annual | C10: Thank-You Letter | F10: Impact Update | I10: Event Invite | L10: Phone Call | N10: Renewal Solicitation | O10: Steady annual fund donor; upgrade potential.
A11: Michael & Linda Torres | B11: Major | C11: Thank-You Call | D11: Impact Update | E11: Board Lunch | G11: Site Visit | H11: Mid-Year Report | J11: Personal Note | K11: Annual Report | M11: Renewal Cultivation | N11: Solicitation | O11: ED relationship. 10-touch plan.
A12: Community Trust Fund | B12: Major | C12: Thank-You Letter | E12: Grant Report | G12: Event Invite | H12: Mid-Year Update | K12: Annual Report | M12: Renewal Convo | N12: Grant Renewal | O12: Institutional donor; coordinate with grants staff.
A46: TOUCHPOINT TYPE KEY (enter these abbreviations in the monthly cells above)
A47: Thank-You Call | B47: Personal phone call to thank donor; use within 48 hrs of gift | H47: Mid-Year Report | I47: Mid-year impact summary showing gift at work
A48: Thank-You Letter | B48: Formal written acknowledgment (IRS-compliant) | H48: Annual Report | I48: Full annual report or personalized impact summary
A49: Impact Update | B49: Personalized story or outcome report tied to their gift | H49: Phone Check-In | I49: Brief relationship call — no ask, just connection
A50: Event Invite | B50: Invite to a cultivation event, program event, or tour | H50: Personal Note | I50: Handwritten card or personal email after a milestone
A51: Board Lunch/Call | B51: Personal outreach from a board member | H51: Renewal Cultivation | I51: Dedicated touchpoint ahead of renewal ask
A52: Site Visit | B52: In-person program tour with staff or beneficiaries | H52: Solicitation | I52: Formal gift ask — face-to-face, phone, or written proposal

Sheet Retention Analysis
A1: DONOR RETENTION ANALYSIS
A2: Module 2: Individual Giving & Donor Relations | Track retention, upgrade rates, and giving trends year over year
A3: ℹ INSTRUCTIONS: Enter data for each fiscal year. All metrics below are calculated automatically. Benchmark: sector average retention is 43–45%. First-time donor retention averages ~18–25%. Target 50%+ overall and 30%+ first-time.
A4: METRIC | B4: FY 2022 | C4: FY 2023 | D4: FY 2024 | E4: FY 2025 | F4: FY 2026 (Proj) | G4: Benchmark / Notes
A5: INPUT DATA
A6: Total Donors (prior year) | G6: Enter: # unique donors who gave last fiscal year
A7: Total Donors (current year) | G7: Enter: # unique donors who gave this fiscal year
A8: Retained Donors (gave both years) | G8: Enter: # donors who gave in BOTH prior and current year
A9: New Donors (first-time) | G9: Enter: # first-time donors this year
A10: First-Time Donors (prior year) | G10: Enter: # first-time donors from LAST year
A11: Retained First-Time Donors | G11: Enter: # of prior year first-timers who gave again this year
A12: Upgraded Donors | G12: Enter: # donors who increased gift vs. prior year
A13: Lapsed Donors | G13: Enter: # donors from prior year who did NOT give this year
A14: Total Individual Giving Revenue ($) | G14: Enter: total revenue from individual donors
A15: CALCULATED METRICS
A16: Overall Retention Rate | B16: =IF(B6=0,"-",B8/B6) -> - | C16: =IF(C6=0,"-",C8/C6) -> - | D16: =IF(D6=0,"-",D8/D6) -> - | E16: =IF(E6=0,"-",E8/E6) -> - | F16: =IF(F6=0,"-",F8/F6) -> - | G16: Sector avg: 43–45%. Target: 50%+
A17: First-Time Donor Retention Rate | B17: =IF(B10=0,"-",B11/B10) -> - | C17: =IF(C10=0,"-",C11/C10) -> - | D17: =IF(D10=0,"-",D11/D10) -> - | E17: =IF(E10=0,"-",E11/E10) -> - | F17: =IF(F10=0,"-",F11/F10) -> - | G17: Sector avg: 18–25%. Target: 30%+
A18: Donor Upgrade Rate | B18: =IF(B8=0,"-",B12/B8) -> - | C18: =IF(C8=0,"-",C12/C8) -> - | D18: =IF(D8=0,"-",D12/D8) -> - | E18: =IF(E8=0,"-",E12/E8) -> - | F18: =IF(F8=0,"-",F12/F8) -> - | G18: Target: 25%+. Higher = better stewardship.
A19: Lapse Rate | B19: =IF(B6=0,"-",B13/B6) -> - | C19: =IF(C6=0,"-",C13/C6) -> - | D19: =IF(D6=0,"-",D13/D6) -> - | E19: =IF(E6=0,"-",E13/E6) -> - | F19: =IF(F6=0,"-",F13/F6) -> - | G19: Target: <50%. Lower = better retention.
A20: New Donor Acquisition | B20: =B9 -> 0 | C20: =C9 -> 0 | D20: =D9 -> 0 | E20: =E9 -> 0 | F20: =F9 -> 0 | G20: Compare vs. lapsed donors to assess net growth.
A21: Net Donor Growth | B21: =IF(B6=0,"-",B7-B6) -> - | C21: =IF(C6=0,"-",C7-C6) -> - | D21: =IF(D6=0,"-",D7-D6) -> - | E21: =IF(E6=0,"-",E7-E6) -> - | F21: =IF(F6=0,"-",F7-F6) -> - | G21: Positive = growing donor base.
A22: Avg. Gift per Donor ($) | B22: =IF(B7=0,"-",B14/B7) -> - | C22: =IF(C7=0,"-",C14/C7) -> - | D22: =IF(D7=0,"-",D14/D7) -> - | E22: =IF(E7=0,"-",E14/E7) -> - | F22: =IF(F7=0,"-",F14/F7) -> - | G22: Track trend: increasing = healthy upgrade culture.
A25: 📊 RETENTION INSIGHT
A26: • Increasing retention by just 10 percentage points can increase 5-year revenue by 50%+ without acquiring any new donors.
A27: • If your lapse rate > 60%, prioritize stewardship improvements over acquisition campaigns.
A28: • First-time donor retention below 25% signals a critical stewardship gap — invest in a 48-hour thank-you protocol immediately.
A29: • A positive net donor growth rate means you're acquiring donors faster than you're losing them — the foundation of a growing program.
A30: • Track upgrade rate separately from retention — it measures whether your stewardship is deepening relationships, not just maintaining them.

Sheet Lapsed Donor Tracker
A1: LAPSED DONOR RE-ENGAGEMENT TRACKER
A2: Module 2: Individual Giving & Donor Relations | Re-engaging lapsed donors is more cost-effective than acquiring new ones
A3: ℹ INSTRUCTIONS: List every donor who has not given in 12+ months. Prioritize by Recency (how long lapsed) and Total Lifetime Giving. Personal re-engagement outperforms mass email — assign a staff or board member to each top lapsed donor.
A4: # | B4: Donor Name | C4: Last Gift Date | D4: Last Gift Amount ($) | E4: Total Lifetime Giving ($) | F4: Lapse Reason (if known) | G4: Re-engagement Method | H4: Re-engagement Date | I4: Outcome | J4: Next Steps / Notes
A5: 1 | B5: James Thompson | C5: 11/15/2024 | D5: 1000 | E5: 3000 | F5: Personal financial difficulty | G5: Phone Call | H5: 05/05/2026 | I5: Positive — continuing stewardship | J5: Shared impact. Will re-solicit in fall 2026.
A6: 2 | B6: Linda Park | C6: 03/20/2023 | D6: 500 | E6: 1500 | F6: Never received thank-you after last gift | G6: Personalized Letter + Call | H6: 04/15/2026 | I6: No response yet | J6: Left voicemail. Send impact report with handwritten note.
A7: 3 | B7: Frank Williams | C7: 06/01/2022 | D7: 2500 | E7: 8000 | F7: Unknown — contact lost | G7: Board Member Call | H7: 05/01/2026 | I7: Reconnected — interested | J7: Board member lunch set for May 20. Strong renewal potential.
A8: 4 | B8: Angela & Thomas Reed | C8: 09/15/2023 | D8: 750 | E8: 2250 | F8: Unsure of impact of giving | G8: Impact Report + Letter | I8: Not yet contacted | J8: Send personalized impact story tied to their original gift purpose.
A9: 5 | B9: Carlos Mendez | C9: 12/31/2023 | D9: 1000 | E9: 4000 | F9: Solicited too frequently | G9: Handwritten Note | H9: 04/20/2026 | I9: Warm — open to reconnection | J9: Sent note. Follow up with invitation to spring event.
A66: RE-ENGAGEMENT STRATEGY GUIDE
A67: Lapse < 18 Months | B67: High priority. Personal phone call or handwritten note. Acknowledge the gap humbly. Share a specific story of impact. Invite them back without pressure.
A68: Lapse 18–36 Months | B68: Medium priority. Personalized letter + impact report. Follow up with a phone call. Share what has changed and what their past giving made possible.
A69: Lapse 36+ Months | B69: Lower priority for major investment, but worth a brief outreach. A mass reactivation email or personal note for high-value lapsed donors. Remove if no response after 2 attempts.
A70: Never Thanked Properly | B70: Highest priority — acknowledge the failure, apologize, and re-engage with a specific impact story. This is the most recoverable lapse reason.
A71: Over-Solicited | B71: Back off! Send a low-ask or no-ask communication first. Re-establish trust before any financial request.
