Workbook

Sheet Dashboard
A1: 🏛 CAPITAL CAMPAIGN PLANNING WORKSHEET
A2: Module 8 Toolkit • Build Your Club Nonprofit Fundraising Course
A3: Complete the yellow-highlighted cells in each sheet. This dashboard auto-updates as you enter data across the workbook.
A5: CAMPAIGN OVERVIEW
A6: Organization Name: | D6: Enter organization name
A7: Campaign Name: | D7: Enter campaign name
A8: Campaign Goal ($):
A9: Quiet Phase Start:
A10: Public Launch Date:
A11: Campaign End Date:
A12: Campaign Director: | D12: Enter name
A14: CAMPAIGN PROGRESS SNAPSHOT
A15: Metric | B15: Value | C15: Source
A16: Campaign Goal ($) | B16: =IF(D8="",0,D8) -> 0 | C16: Dashboard — Campaign Goal
A17: Total Raised (Gifts Received) | B17: =SUMIF('Prospect Pool'!G:G,"Gift Received",'Prospect Pool'!F:F) -> 250000 | C17: Prospect Pool sheet
A18: Total Pledged (All Commitments) | B18: =SUMIF('Prospect Pool'!G:G,"Pledged",'Prospect Pool'!F:F) -> 100000 | C18: Prospect Pool sheet
A19: Total Committed (Raised + Pledged) | B19: =B17+B18 -> 350000 | C19: Calculated
A20: % of Goal Raised | B20: =IF(B16=0,"-",B17/B16) -> - | C20: Calculated
A21: % of Goal Committed | B21: =IF(B16=0,"-",B19/B16) -> - | C21: Calculated
A22: Remaining to Goal | B22: =IF(B16=0,"-",B16-B17) -> - | C22: Calculated
A23: # Prospects in Pool | B23: =COUNTA('Prospect Pool'!A:A)-2 -> 10 | C23: Prospect Pool sheet
A24: # Gifts Received | B24: =COUNTIF('Prospect Pool'!G:G,"Gift Received") -> 1 | C24: Prospect Pool sheet
A25: # Active Prospects | B25: =COUNTIF('Prospect Pool'!G:G,"In Cultivation")+COUNTIF('Prospect Pool'!G:G,"Solicited")+COUNTIF('Prospect Pool'!G:G,"Pledged") -> 4 | C25: Prospect Pool sheet
A27: CAMPAIGN PHASE TRACKER
A28: Phase | B28: Description | C28: Target Start | D28: Target End | E28: Status
A29: 1 – Planning & Feasibility | B29: Conduct feasibility study, finalize goal, recruit leadership | E29: Not Started
A30: 2 – Quiet Phase | B30: Solicit lead gifts; secure 50–70% of goal before public launch | E30: Not Started
A31: 3 – Public Launch | B31: Announce campaign publicly; broaden donor outreach | E31: Not Started
A32: 4 – Campaign Push | B32: Intensive solicitation, events, and mid-level donor cultivation | E32: Not Started
A33: 5 – Final Sprint | B33: Close remaining gaps; cultivate lapsed prospects | E33: Not Started
A34: 6 – Celebration & Stewardship | B34: Thank donors, recognize gifts, begin stewardship | E34: Not Started

Sheet Feasibility Assessment
A1: 🔍 CAMPAIGN FEASIBILITY ASSESSMENT
A2: Rate each factor 1–5 (1 = Not Ready, 5 = Fully Ready). Scores auto-calculate.
A3: A total score of 75%+ suggests readiness to proceed. Scores below 60% indicate areas requiring attention before launching.
A5: INTERNAL READINESS
A6: Factor | B6: Description | C6: Your Score (1–5) | D6: Weight | E6: Weighted Score | F6: Notes
A7: Board Engagement | B7: Board members are informed, enthusiastic, and personally committed to giving | D7: 5 | E7: =IF(C7="","-",C7*D7) -> - | F7: Source: Internal assessment
A8: Leadership Giving | B8: Board and key volunteers have made or committed to major gifts | D8: 5 | E8: =IF(C8="","-",C8*D8) -> - | F8: Source: Internal assessment
A9: Staff Capacity | B9: Development staff is adequate to manage campaign workload | D9: 4 | E9: =IF(C9="","-",C9*D9) -> - | F9: Source: Internal assessment
A10: Track Record | B10: Organization has demonstrated success with past fundraising campaigns | D10: 4 | E10: =IF(C10="","-",C10*D10) -> - | F10: Source: Internal assessment
A11: Financial Health | B11: Organization is fiscally stable with clean audits and strong reserves | D11: 5 | E11: =IF(C11="","-",C11*D11) -> - | F11: Source: Internal assessment
A12: Case for Support | B12: A compelling, urgent, and community-validated case exists | D12: 5 | E12: =IF(C12="","-",C12*D12) -> - | F12: Source: Internal assessment
A13: Data & Systems | B13: Donor database is current, clean, and capable of tracking campaign activity | D13: 3 | E13: =IF(C13="","-",C13*D13) -> - | F13: Source: Internal assessment
A14: Prospect Pipeline | B14: A robust list of 3–5× the goal in qualified prospects exists | D14: 4 | E14: =IF(C14="","-",C14*D14) -> - | F14: Source: Internal assessment
A16: EXTERNAL READINESS
A17: Factor | B17: Description | C17: Your Score (1–5) | D17: Weight | E17: Weighted Score | F17: Notes
A18: Community Need | B18: Community clearly understands and supports the campaign purpose | D18: 5 | E18: =IF(C18="","-",C18*D18) -> - | F18: Source: External assessment
A19: Peer Institutions | B19: Similar organizations have recently run successful campaigns | D19: 3 | E19: =IF(C19="","-",C19*D19) -> - | F19: Source: External assessment
A20: Economic Climate | B20: Local/national economy supports major philanthropic investment | D20: 4 | E20: =IF(C20="","-",C20*D20) -> - | F20: Source: External assessment
A21: Donor Capacity | B21: Enough high-capacity donors in your community to reach goal | D21: 4 | E21: =IF(C21="","-",C21*D21) -> - | F21: Source: External assessment
A22: Competition | B22: No major competing campaigns from peer organizations in same window | D22: 3 | E22: =IF(C22="","-",C22*D22) -> - | F22: Source: External assessment
A23: Timing | B23: Campaign timetable avoids conflicts with elections, crises, or other priorities | D23: 4 | E23: =IF(C23="","-",C23*D23) -> - | F23: Source: External assessment
A25: SCORE SUMMARY
A26: Internal Weighted Total | B26: =SUMIF(E7:E14,"<>#VALUE!") -> 0
A27: Internal Maximum Possible | B27: =SUMPRODUCT(D7:D14)*5 -> 175
A28: Internal Readiness % | B28: =IF(B27=0,"-",B26/B27) -> 0
A29: External Weighted Total | B29: =SUMIF(E18:E23,"<>#VALUE!") -> 0
A30: External Maximum Possible | B30: =SUMPRODUCT(D18:D23)*5 -> 115
A31: External Readiness % | B31: =IF(B30=0,"-",B29/B30) -> 0
A32: Overall Score % | B32: =IF((B27+B30)=0,"-",(B26+B29)/(B27+B30)) -> 0
A33: Recommendation | B33: =IF(B32="-","Enter scores above",IF(B32>=0.75,"✅ Ready to Proceed",IF(B32>=0.6,"⚠️ Proceed with Caution","❌ Not Ready — Address Gaps First"))) -> ❌ Not Ready — Address Gaps First

Sheet Gift Range Chart
A1: 🎯 GIFT RANGE CHART (CAMPAIGN PYRAMID)
A2: The classic campaign pyramid: a small number of major gifts will account for 80–90% of your total.
A3: Enter your Campaign Goal on the Dashboard. Adjust gift levels, # of gifts needed, and # of prospects needed to model your campaign structure.
A5: CAMPAIGN SUMMARY
A6: Campaign Goal ($) | C6: Total Gifts Needed | E6: Total Prospects Needed | G6: Goal Coverage ($)
A7: =Dashboard!D8 -> 0 | C7: =SUM(D9:D25) -> 2286 | E7: =SUM(E9:E25) -> 2020000 | G7: =SUMPRODUCT(C9:C25,D9:D25) -> 545124
A9: Gift Level | B9: Gift Amount ($) | C9: # Gifts Needed | D9: # Prospects (3:1) | E9: Subtotal ($) | F9: Gifts Received | G9: Amount Raised | H9: % of Goal | I9: Gap ($)
A10: Lead Gift | B10: 250000 | C10: 1 | D10: 3 | E10: =B10*C10 -> 250000 | G10: =IF(F10="",0,F10*B10) -> 0 | H10: =IF(Dashboard!D8=0,"-",G10/Dashboard!D8) -> - | I10: =E10-G10 -> 250000
A11: Major Gift 1 | B11: 100000 | C11: 2 | D11: 6 | E11: =B11*C11 -> 200000 | G11: =IF(F11="",0,F11*B11) -> 0 | H11: =IF(Dashboard!D8=0,"-",G11/Dashboard!D8) -> - | I11: =E11-G11 -> 200000
A12: Major Gift 2 | B12: 50000 | C12: 3 | D12: 9 | E12: =B12*C12 -> 150000 | G12: =IF(F12="",0,F12*B12) -> 0 | H12: =IF(Dashboard!D8=0,"-",G12/Dashboard!D8) -> - | I12: =E12-G12 -> 150000
A13: Major Gift 3 | B13: 25000 | C13: 5 | D13: 15 | E13: =B13*C13 -> 125000 | G13: =IF(F13="",0,F13*B13) -> 0 | H13: =IF(Dashboard!D8=0,"-",G13/Dashboard!D8) -> - | I13: =E13-G13 -> 125000
A14: Mid-Level 1 | B14: 10000 | C14: 8 | D14: 24 | E14: =B14*C14 -> 80000 | G14: =IF(F14="",0,F14*B14) -> 0 | H14: =IF(Dashboard!D8=0,"-",G14/Dashboard!D8) -> - | I14: =E14-G14 -> 80000
A15: Mid-Level 2 | B15: 5000 | C15: 12 | D15: 36 | E15: =B15*C15 -> 60000 | G15: =IF(F15="",0,F15*B15) -> 0 | H15: =IF(Dashboard!D8=0,"-",G15/Dashboard!D8) -> - | I15: =E15-G15 -> 60000
A16: Mid-Level 3 | B16: 2500 | C16: 20 | D16: 60 | E16: =B16*C16 -> 50000 | G16: =IF(F16="",0,F16*B16) -> 0 | H16: =IF(Dashboard!D8=0,"-",G16/Dashboard!D8) -> - | I16: =E16-G16 -> 50000
A17: Leadership Annual | B17: 1000 | C17: 30 | D17: 90 | E17: =B17*C17 -> 30000 | G17: =IF(F17="",0,F17*B17) -> 0 | H17: =IF(Dashboard!D8=0,"-",G17/Dashboard!D8) -> - | I17: =E17-G17 -> 30000
A18: General Campaign | B18: 500 | C18: 50 | D18: 150 | E18: =B18*C18 -> 25000 | G18: =IF(F18="",0,F18*B18) -> 0 | H18: =IF(Dashboard!D8=0,"-",G18/Dashboard!D8) -> - | I18: =E18-G18 -> 25000
A19: Community Support | B19: 250 | C19: 100 | D19: 300 | E19: =B19*C19 -> 25000 | G19: =IF(F19="",0,F19*B19) -> 0 | H19: =IF(Dashboard!D8=0,"-",G19/Dashboard!D8) -> - | I19: =E19-G19 -> 25000
A20: Friend | B20: 100 | C20: 150 | D20: 450 | E20: =B20*C20 -> 15000 | G20: =IF(F20="",0,F20*B20) -> 0 | H20: =IF(Dashboard!D8=0,"-",G20/Dashboard!D8) -> - | I20: =E20-G20 -> 15000
A21: TOTALS | C21: =SUM(C10:C20) -> 381 | D21: =SUM(D10:D20) -> 1143 | E21: =SUM(E10:E20) -> 1010000 | G21: =SUM(G10:G20) -> 0 | H21: =IF(Dashboard!D8=0,"-",G21/Dashboard!D8) -> - | I21: =SUM(I10:I20) -> 1010000

Sheet Prospect Pool
A1: 👥 PROSPECT POOL TRACKER
A2: Track every campaign prospect — from identification through gift receipt and stewardship.
A3: Status options: Identified | In Cultivation | Solicited | Pledged | Gift Received | Declined | Lapsed
A4: Total Prospects | B4: In Cultivation | C4: Solicited | D4: Pledged | E4: Gifts Received | F4: Total Raised ($) | G4: Total Pledged ($)
A5: =COUNTA(A7:A200) -> 7 | B5: =COUNTIF(G7:G200,"In Cultivation") -> 2 | C5: =COUNTIF(G7:G200,"Solicited") -> 1 | D5: =COUNTIF(G7:G200,"Pledged") -> 1 | E5: =COUNTIF(G7:G200,"Gift Received") -> 1 | F5: =SUMIF(G7:G200,"Gift Received",F7:F200) -> 250000 | G5: =SUMIF(G7:G200,"Pledged",F7:F200) -> 100000
A7: Prospect Name | B7: Gift Level Target | C7: Capacity Estimate ($) | D7: Ask Amount ($) | E7: Assigned Solicitor | F7: Gift/Pledge Amount ($) | G7: Status | H7: Last Contact | I7: Next Action | J7: Next Action Date | K7: Notes
A8: Smith, Robert & Mary | B8: Lead Gift | C8: 500000 | D8: 250000 | E8: CEO / Board Chair | F8: 250000 | G8: Gift Received | H8: 2025-03-01 | I8: Send recognition letter | J8: 2025-03-15 | K8: Naming gift for main building
A9: Johnson Foundation | B9: Major Gift 1 | C9: 200000 | D9: 100000 | E9: Executive Director | F9: 100000 | G9: Pledged | H9: 2025-04-10 | I9: Pledge payment follow-up | J9: 2025-06-01 | K9: 5-year pledge, $20K/yr
A10: Williams, Dr. Susan | B10: Major Gift 2 | C10: 80000 | D10: 50000 | E10: Board Member | G10: Solicited | H10: 2025-04-20 | I10: Await decision | J10: 2025-05-15 | K10: Met at cultivation dinner
A11: Chen, Michael | B11: Major Gift 2 | C11: 75000 | D11: 50000 | E11: Development Dir. | G11: In Cultivation | H11: 2025-03-28 | I11: Schedule site visit | J11: 2025-05-01 | K11: Long-time donor, capacity confirmed
A12: Patel, Anita | B12: Major Gift 3 | C12: 40000 | D12: 25000 | E12: Board Member | G12: In Cultivation | H12: 2025-04-05 | I12: Invite to leadership breakfast | J12: 2025-05-10 | K12: Interested in scholarship fund
A13: Thompson Corp. | B13: Mid-Level 1 | C13: 20000 | D13: 10000 | E13: Executive Director | G13: Identified | H13: 2025-02-15 | I13: Request introductory meeting | J13: 2025-05-20 | K13: Referred by board member

Sheet Campaign Timeline
A1: 📅 CAMPAIGN TIMELINE & MILESTONES
A2: Track key milestones across each campaign phase. Update status as you progress.
A3: Status options: Not Started | In Progress | Completed | Delayed | Cancelled
A5: Phase / Milestone | B5: Owner | C5: Target Start | D5: Target End | E5: Actual Complete | F5: Status | G5: % Done | H5: Notes
A6: PHASE 1: PLANNING & FEASIBILITY
A7: Hire campaign counsel / feasibility consultant | B7: Executive Director | F7: Not Started
A8: Conduct feasibility study (interviews) | B8: Campaign Counsel | F8: Not Started
A9: Analyze study results and set campaign goal | B9: Board + Staff | F9: Not Started
A10: Identify and recruit campaign leadership volunteers | B10: Board Chair | F10: Not Started
A11: Draft Case for Support | B11: Development Dir. | F11: Not Started
A12: Finalize campaign structure and timeline | B12: Executive Director | F12: Not Started
A13: PHASE 2: QUIET PHASE
A14: Identify and prioritize top 10–20 prospects | B14: Development Dir. | F14: Not Started
A15: Begin cultivation of lead gift prospects | B15: CEO / Board Chair | F15: Not Started
A16: Solicit lead gift (50% of goal) | B16: Campaign Chair | F16: Not Started
A17: Secure 60–70% of goal in quiet phase gifts | B17: Development Dir. | F17: Not Started
A18: Plan public launch event | B18: Events Team | F18: Not Started
A19: PHASE 3: PUBLIC LAUNCH
A20: Host public campaign launch event | B20: Executive Director | F20: Not Started
A21: Issue press release and media campaign | B21: Communications | F21: Not Started
A22: Launch direct mail / email campaign | B22: Development Dir. | F22: Not Started
A23: Begin mid-level donor cultivation and solicitation | B23: Major Gifts Officer | F23: Not Started
A24: PHASE 4: INTENSIVE PUSH
A25: Host cultivation events for mid-level prospects | B25: Events Team | F25: Not Started
A26: Deploy board members in peer-to-peer asks | B26: Board Chair | F26: Not Started
A27: Follow up with all outstanding proposals | B27: Development Dir. | F27: Not Started
A28: Conduct mid-campaign board check-in | B28: Executive Director | F28: Not Started
A29: PHASE 5: FINAL SPRINT
A30: Re-solicit undecided prospects | B30: Campaign Team | F30: Not Started
A31: Launch challenge match campaign (if applicable) | B31: Development Dir. | F31: Not Started
A32: Close all open proposals | B32: Major Gifts Officer | F32: Not Started
A33: PHASE 6: CELEBRATION & STEWARDSHIP
A34: Host donor recognition celebration event | B34: Events Team | F34: Not Started
A35: Install donor recognition wall / naming plaques | B35: Facilities | F35: Not Started
A36: Send personal thank-you letters from CEO & Board | B36: Executive Director | F36: Not Started
A37: Begin ongoing stewardship of all campaign donors | B37: Development Dir. | F37: Not Started

Sheet Campaign Budget
A1: 💰 CAMPAIGN BUDGET TRACKER
A2: Track campaign expenses against budget. Industry standard: campaign costs should be 5–15% of goal.
A3: Enter budgeted amounts in column C and actual expenditures in column E as invoices are paid. Notes column for vendor/context.
A4: Total Budget ($) | B4: Total Actual ($) | C4: Budget Remaining ($) | D4: % of Campaign Goal | E4: Status
A5: =SUM(C8:C50) -> 297500 | B5: =SUM(E8:E50) -> 0 | C5: =A5-B5 -> 297500 | D5: =IF(Dashboard!D8=0,"-",A5/Dashboard!D8) -> - | E5: =IF(Dashboard!D8=0,"-",IF(A5/Dashboard!D8<=0.1,"✅ Within Target",IF(A5/Dashboard!D8<=0.15,"⚠️ Monitor Closely","❌ Over Industry Norm"))) -> -
A7: Category | B7: Line Item | C7: Budget ($) | D7: # Units | E7: Actual ($) | F7: Variance ($) | G7: Paid? | H7: Notes / Vendor
A8: Consulting & Professional | B8: Campaign Counsel / Feasibility Study | C8: 25000 | D8: 1 | F8: =C8-E8 -> 25000
A9: Consulting & Professional | B9: Graphic Design (Case for Support, collateral) | C9: 5000 | D9: 1 | F9: =C9-E9 -> 5000
A10: Consulting & Professional | B10: Legal Fees (gift agreements, naming rights) | C10: 3000 | D10: 1 | F10: =C10-E10 -> 3000
A11: Consulting & Professional | B11: Accounting / Audit Support | C11: 2000 | D11: 1 | F11: =C11-E11 -> 2000
A12: Communications & Marketing | B12: Case for Support Printing | C12: 2500 | D12: 500 | F12: =C12-E12 -> 2500
A13: Communications & Marketing | B13: Campaign Website / Microsite | C13: 3000 | D13: 1 | F13: =C13-E13 -> 3000
A14: Communications & Marketing | B14: Video Production (campaign video) | C14: 8000 | D14: 1 | F14: =C14-E14 -> 8000
A15: Communications & Marketing | B15: Photography | C15: 1500 | D15: 1 | F15: =C15-E15 -> 1500
A16: Communications & Marketing | B16: Direct Mail Appeals | C16: 4000 | D16: 2500 | F16: =C16-E16 -> 4000
A17: Events | B17: Cultivation Dinners | C17: 6000 | D17: 3 | F17: =C17-E17 -> 6000
A18: Events | B18: Public Launch Event | C18: 8000 | D18: 1 | F18: =C18-E18 -> 8000
A19: Events | B19: Donor Recognition Celebration | C19: 5000 | D19: 1 | F19: =C19-E19 -> 5000
... A30: Contingency | B30: Contingency Reserve (5%) | C30: 6250 | D30: 1 | F30: =C30-E30 -> 6250
A31: TOTAL | C31: =SUM(C8:C30) -> 148750 | E31: =SUM(E8:E30) -> 0 | F31: =C31-E31 -> 148750

Sheet Donor Recognition
A1: 🏆 DONOR RECOGNITION PLAN
A2: Map recognition opportunities to gift levels. Ensure naming rights and recognition are documented before solicitation.
A3: Naming opportunities must be approved by the board before being offered to donors. Complete the 'Board Approved?' column before soliciting.
A5: RECOGNITION LEVELS & NAMING OPPORTUNITIES
A6: Gift Level / Range | B6: Recognition Tier Name | C6: Naming Opportunity | D6: Recognition Type | E6: Max Available | F6: # Claimed | G6: Remaining | H6: Board Approved? | I6: Notes
A7: $250,000+ | B7: Founding Patron | C7: Main Building / Primary Facility | D7: Permanent exterior signage, named space | E7: 1 | G7: =E7-F7 -> 1 | H7: Yes | I7: Board Resolution #2025-01
A8: $100,000–$249,999 | B8: Benefactor | C8: Auditorium / Large Program Space | D8: Interior naming plaque + recognition wall | E8: 2 | G8: =E8-F8 -> 2 | H8: Yes | I8: Pending final approval
A9: $50,000–$99,999 | B9: Platinum Sponsor | C9: Conference Room / Training Center | D9: Named room plaque + donor wall | E9: 3 | G9: =E9-F9 -> 3 | H9: Yes
A10: $25,000–$49,999 | B10: Gold Sponsor | C10: Scholarship Fund / Named Program | D10: Annual report feature + named fund | E10: 5 | G10: =E10-F10 -> 5 | H10: Yes
A11: $10,000–$24,999 | B11: Silver Sponsor | C11: Garden / Outdoor Feature | D11: Outdoor bench/plaque + donor wall listing | E11: 8 | G11: =E11-F11 -> 8 | H11: Pending
A12: $5,000–$9,999 | B12: Bronze Sponsor | C12: Technology Resource Center | D12: Digital donor board listing + social media | E12: 12 | G12: =E12-F12 -> 12 | H12: Pending
A13: $2,500–$4,999 | B13: Leadership Circle | C13: Annual Recognition Event Invitation | D13: Event invitation + program listing | E13: 20 | G13: =E13-F13 -> 20 | H13: Yes
A14: $1,000–$2,499 | B14: Campaign Builder | C14: Donor Recognition Wall | D14: Engraved name on donor wall | E14: 30 | G14: =E14-F14 -> 30 | H14: Yes
A15: $500–$999 | B15: Community Champion | C15: Donor Wall Listing | D15: Printed donor wall listing | E15: 50 | G15: =E15-F15 -> 50 | H15: Yes
A16: $100–$499 | B16: Friend of the Campaign | C16: Annual Report Listing | D16: Name in annual report | E16: 150 | G16: =E16-F16 -> 150 | H16: Yes
A17: Any Amount | B17: Campaign Supporter | C17: Email & Social Media Recognition | D17: Social media shoutout (with permission) | H17: Yes
A19: STEWARDSHIP TOUCHPOINT PLAN BY RECOGNITION TIER
A20: Recognition Tier | B20: Thank-You Letter | C20: Personal Call | D20: Recognition Event | E20: Annual Impact Report | F20: Site Visit | G20: Named Space Ceremony | H20: Custom Touchpoint
A21: Founding Patron ($250K+) | B21: Within 24 hrs | C21: CEO within 48 hrs | D21: VIP Seat | E21: Custom report | F21: Annual | G21: Yes — Ceremony | H21: Board dinner, annual meeting
A22: Benefactor ($100K+) | B22: Within 24 hrs | C22: CEO within 48 hrs | D22: VIP Seat | E22: Custom report | F22: Annual | G22: Yes — Invited | H22: Annual personal update meeting
A23: Platinum ($50K+) | B23: Within 48 hrs | C23: Dev. Dir. within 72 hrs | D23: VIP Seat | E23: Personalized insert | F23: Bi-annual | G23: Invited | H23: Holiday card, program update
A24: Gold ($25K+) | B24: Within 48 hrs | C24: Board Member call | D24: Invited | E24: Personalized insert | F24: Annual | G24: Invited | H24: Holiday card
A25: Silver ($10K+) | B25: Within 72 hrs | C25: Staff call | D25: Invited | E25: Annual report | F25: As appropriate | G25: No | H25: Email update
A26: Bronze ($5K+) | B26: Within 72 hrs | C26: Staff call | D26: Invited | E26: Annual report | F26: No | G26: No | H26: Email update
A27: Leadership Circle ($1K+) | B27: Within 1 week | C27: No | D27: Invited | E27: Annual report listing | F27: No | G27: No | H27: Social media recognition
A28: Friend / Supporter (<$1K) | B28: Within 1 week | C28: No | D28: General invite | E28: Annual report listing | F28: No | G28: No | H28: Email thank-you
