Workbook

Sheet Dashboard
A1: 📊 FUNDRAISING DASHBOARD & METRICS TRACKER
A2: Module 9 Toolkit • Build Your Club Nonprofit Fundraising Course
A3: Enter your fiscal year and goals below. All KPIs pull live from the data sheets — enter data there to populate this dashboard.
A5: ORGANIZATION & FISCAL YEAR SETTINGS
A6: Organization Name: | D6: Enter organization name
A7: Fiscal Year: | D7: FY2026
A8: FY Start Date:
A9: FY End Date:
A10: Annual Fund Goal ($):
A12: REVENUE METRICS
A13: Total Revenue YTD ($) | B13: Annual Fund Goal ($) | C13: % of Goal Achieved | D13: Remaining to Goal ($) | E13: Avg Monthly Revenue ($) | F13: Revenue vs. Prior Year
A14: =SUM('Monthly Progress'!C18:C29) -> 0 | B14: =D10 -> 0 | C14: =IF(D10=0,"-",A14/D10) -> - | D14: =IF(D10=0,"-",D10-A14) -> - | E14: =IF(COUNTA('Monthly Progress'!C18:C29)=0,"-",A14/COUNTA('Monthly Progress'!C18:C29)) -> 0 | F14: =IF('Donor Retention'!A7=0,"-",A14/'Donor Retention'!A7-1) -> -
A16: DONOR METRICS
A17: Total Donors YTD | B17: New Donors | C17: Renewed Donors | D17: Lapsed Donors | E17: Retention Rate | F17: Avg Gift Size ($)
A18: =COUNTA('Donor Retention'!A10:A209) -> 10 | B18: =COUNTIF('Donor Retention'!E10:E209,"New") -> 1 | C18: =COUNTIF('Donor Retention'!E10:E209,"Renewed") -> 3 | D18: =COUNTIF('Donor Retention'!E10:E209,"Lapsed") -> 1 | E18: =IF((C18+D18)=0,"-",C18/(C18+D18)) -> 0.75 | F18: =IF(A18=0,"-",'Monthly Progress'!C30/A18) -> 0
A20: FUNDRAISING EFFICIENCY METRICS
A21: Cost to Raise $1 | B21: Return on Investment | C21: # of Gifts YTD | D21: Gifts from Major Donors ($) | E21: Major Gift % of Revenue | F21: Upgrade Rate
A22: =IF('Appeal Performance'!E7=0,"-",'Appeal Performance'!E7/'Appeal Performance'!D7) -> 0.10784949 | B22: =IF('Appeal Performance'!E7=0,"-",'Appeal Performance'!D7/'Appeal Performance'!E7) -> 9.2721815 | C22: =COUNTA('Donor Retention'!A10:A209) -> 10 | D22: =SUMIF('Donor Pyramid'!A9:A19,"Major Donor",'Donor Pyramid'!E9:E19) -> 0 | E22: =IF(A14=0,"-",D22/A14) -> - | F22: =IF(A18=0,"-",COUNTIF('Donor Retention'!E10:E209,"Upgraded")/A18) -> 0.2
A24: INDUSTRY BENCHMARK QUICK REFERENCE
A25: Metric | B25: Industry Avg | C25: Your Score | D25: Status
A26: Overall Donor Retention Rate | B26: 45–50% | C26: =IF(E18="-","—",TEXT(E18,"0.0%")) -> 75.0% | D26: =IF(E18="-","—",IF(E18>=0.5,"✅ At/Above Avg",IF(E18>=0.4,"⚠️ Near Avg","❌ Below Avg"))) -> ✅ At/Above Avg
A27: New Donor Retention Rate | B27: 20–25% | C27: Enter manually
A28: Average Gift Size | B28: $150–$250 | C28: =IF(F18="-","—",TEXT(F18,"$#,##0")) -> $0
A29: Cost to Raise $1 | B29: $0.15–$0.25 | C29: =IF(A22="-","—",TEXT(A22,"$0.00")) -> $0.11 | D29: =IF(A22="-","—",IF(A22<=0.2,"✅ Efficient",IF(A22<=0.3,"⚠️ Monitor","❌ High Cost"))) -> ✅ Efficient
A30: Major Gift % of Revenue | B30: 60–80% | C30: =IF(E22="-","—",TEXT(E22,"0.0%")) -> — | D30: =IF(E22="-","—",IF(E22>=0.6,"✅ Healthy",IF(E22>=0.4,"⚠️ Growing","❌ Low"))) -> —
A31: Online Giving % of Revenue | B31: 15–25% | C31: See Appeal Performance

Sheet Donor Retention
A1: 🔄 DONOR RETENTION ANALYSIS
A2: Track donor giving year-over-year. Identify LYBUNT, SYBUNT, new, and lapsed donors.
A3: LYBUNT = Last Year But Unfortunately Not This Year. SYBUNT = Some Year But Unfortunately Not This Year. Status auto-calculates from giving columns.
A5: YEAR-OVER-YEAR SUMMARY
A6: Prior Year Revenue ($) | B6: Current Year Revenue ($) | C6: Revenue Growth ($) | D6: Revenue Growth % | E6: Prior Year Donors | F6: Current Year Donors | G6: Retention Rate | H6: Attrition Rate
B7: =SUM('Monthly Progress'!C18:C29) -> 0 | C7: =B7-A7 -> 0 | D7: =IF(A7=0,"-",B7/A7-1) -> - | F7: =COUNTA(A10:A209) -> 10 | G7: =IF(E7=0,"-",COUNTIF(E10:E209,"Renewed")/E7) -> - | H7: =IF(E7=0,"-",COUNTIF(E10:E209,"Lapsed")/E7) -> -
A9: Donor Name | B9: Donor ID | C9: Prior Year Gift ($) | D9: Current Year Gift ($) | E9: Status | F9: Giving Streak (Yrs) | G9: First Gift Year | H9: Cumulative Giving ($) | I9: Segment | J9: Notes
A10: Smith, Robert | B10: D001 | C10: 500 | D10: 500 | E10: Renewed | F10: 5 | G10: 2020 | H10: 2500 | I10: Mid-Level | J10: Consistent annual donor
A11: Johnson, Mary | B11: D002 | C11: 1000 | D11: 1500 | E11: Upgraded | F11: 3 | G11: 2022 | H11: 3500 | I11: Mid-Level | J11: Increased gift — acknowledge!
A12: Williams, David | B12: D003 | C12: 250 | E12: Lapsed | F12: 2 | G12: 2023 | H12: 500 | I12: General | J12: No gift this year — follow up
A13: Brown, Patricia | B13: D004 | D13: 100 | E13: New | F13: 1 | G13: 2026 | H13: 100 | I13: General | J13: First-time donor
A14: Jones, Michael | B14: D005 | C14: 5000 | D14: 5000 | E14: Renewed | F14: 7 | G14: 2018 | H14: 35000 | I14: Major Donor | J14: Annual campaign leadership gift
A15: Garcia, Linda | B15: D006 | C15: 150 | E15: LYBUNT | F15: 1 | G15: 2025 | H15: 150 | I15: General | J15: Contact before year-end
A16: Martinez, James | B16: D007 | C16: 75 | E16: SYBUNT | F16: 0 | G16: 2023 | H16: 225 | I16: General | J16: Lapsed 2+ years
A17: Anderson, Barbara | B17: D008 | C17: 2500 | D17: 3000 | E17: Upgraded | F17: 4 | G17: 2022 | H17: 10000 | I17: Mid-Level | J17: Moving toward major gift range
A18: Taylor, Charles | B18: D009 | C18: 10000 | D18: 10000 | E18: Renewed | F18: 10 | G18: 2016 | H18: 100000 | I18: Major Donor | J18: Long-term major donor
A19: Thomas, Susan | B19: D010 | D19: 250 | E19: Recaptured | F19: 1 | G19: 2023 | H19: 500 | I19: General | J19: Lapsed but re-engaged this year

Sheet Revenue by Source
A1: 💵 REVENUE BY SOURCE TRACKER
A2: Track revenue diversification across all funding streams. Healthy nonprofits diversify across 4+ sources.
A3: Enter actual revenue in column D. Budgeted amounts in column C. The % of Total and Diversification Score auto-calculate.
A5: REVENUE SUMMARY
A6: Total Budget ($) | B6: Total Actual ($) | C6: Variance ($) | D6: % of Budget | E6: # Active Sources | F6: Diversification Score
A7: =SUM(C9:C30) -> 1136000 | B7: =SUM(D9:D30) -> 0 | C7: =A7-B7 -> 1136000 | D7: =IF(A7=0,"-",B7/A7) -> 0 | E7: =COUNTIF(D9:D30,">"&0) -> 0 | F7: =IF(E7=0,"-",IF(E7>=5,"✅ Diversified",IF(E7>=3,"⚠️ Moderate","❌ Concentrated"))) -> -
A8: Funding Source | B8: Category | C8: Budget ($) | D8: Actual ($) | E8: Variance ($) | F8: % of Total | G8: Prior Year ($) | H8: YoY Change | I8: Notes
A9: Major Gifts ($10K+) | B9: Individual Giving | C9: 150000 | E9: =C9-D9 -> 150000 | F9: =IF(SUM(D9:D30)=0,"-",D9/SUM(D9:D30)) -> - | G9: 125000 | H9: =IF(G9=0,"-",D9/G9-1) -> -1
A10: Mid-Level Gifts ($1K–$9,999) | B10: Individual Giving | C10: 75000 | E10: =C10-D10 -> 75000 | F10: =IF(SUM(D9:D30)=0,"-",D10/SUM(D9:D30)) -> - | G10: 68000 | H10: =IF(G10=0,"-",D10/G10-1) -> -1
A11: General Annual Fund (<$1K) | B11: Individual Giving | C11: 40000 | E11: =C11-D11 -> 40000 | F11: =IF(SUM(D9:D30)=0,"-",D11/SUM(D9:D30)) -> - | G11: 38000 | H11: =IF(G11=0,"-",D11/G11-1) -> -1
A12: Planned Gifts / Bequests | B12: Individual Giving | C12: 20000 | E12: =C12-D12 -> 20000 | F12: =IF(SUM(D9:D30)=0,"-",D12/SUM(D9:D30)) -> - | G12: 0 | H12: =IF(G12=0,"-",D12/G12-1) -> -
A13: Corporate Sponsorships | B13: Corporate | C13: 35000 | E13: =C13-D13 -> 35000 | F13: =IF(SUM(D9:D30)=0,"-",D13/SUM(D9:D30)) -> - | G13: 30000 | H13: =IF(G13=0,"-",D13/G13-1) -> -1
A14: Corporate Matching Gifts | B14: Corporate | C14: 10000 | E14: =C14-D14 -> 10000 | F14: =IF(SUM(D9:D30)=0,"-",D14/SUM(D9:D30)) -> - | G14: 8000 | H14: =IF(G14=0,"-",D14/G14-1) -> -1
A15: Foundation Grants | B15: Grants | C15: 60000 | E15: =C15-D15 -> 60000 | F15: =IF(SUM(D9:D30)=0,"-",D15/SUM(D9:D30)) -> - | G15: 55000 | H15: =IF(G15=0,"-",D15/G15-1) -> -1
A16: Government Grants | B16: Grants | C16: 30000 | E16: =C16-D16 -> 30000 | F16: =IF(SUM(D9:D30)=0,"-",D16/SUM(D9:D30)) -> - | G16: 28000 | H16: =IF(G16=0,"-",D16/G16-1) -> -1
A17: Annual Gala / Benefit Event | B17: Events | C17: 45000 | E17: =C17-D17 -> 45000 | F17: =IF(SUM(D9:D30)=0,"-",D17/SUM(D9:D30)) -> - | G17: 40000 | H17: =IF(G17=0,"-",D17/G17-1) -> -1
A18: Golf Tournament | B18: Events | C18: 20000 | E18: =C18-D18 -> 20000 | F18: =IF(SUM(D9:D30)=0,"-",D18/SUM(D9:D30)) -> - | G18: 18000 | H18: =IF(G18=0,"-",D18/G18-1) -> -1
A19: Other Special Events | B19: Events | C19: 10000 | E19: =C19-D19 -> 10000 | F19: =IF(SUM(D9:D30)=0,"-",D19/SUM(D9:D30)) -> - | G19: 9000 | H19: =IF(G19=0,"-",D19/G19-1) -> -1
A20: Online / Peer-to-Peer | B20: Digital | C20: 15000 | E20: =C20-D20 -> 15000 | F20: =IF(SUM(D9:D30)=0,"-",D20/SUM(D9:D30)) -> - | G20: 10000 | H20: =IF(G20=0,"-",D20/G20-1) -> -1
A21: Direct Mail Appeals | B21: Annual Fund | C21: 12000 | E21: =C21-D21 -> 12000 | F21: =IF(SUM(D9:D30)=0,"-",D21/SUM(D9:D30)) -> - | G21: 11000 | H21: =IF(G21=0,"-",D21/G21-1) -> -1
A22: Email Campaigns | B22: Annual Fund | C22: 5000 | E22: =C22-D22 -> 5000 | F22: =IF(SUM(D9:D30)=0,"-",D22/SUM(D9:D30)) -> - | G22: 4000 | H22: =IF(G22=0,"-",D22/G22-1) -> -1
A23: Membership Dues | B23: Membership | C23: 8000 | E23: =C23-D23 -> 8000 | F23: =IF(SUM(D9:D30)=0,"-",D23/SUM(D9:D30)) -> - | G23: 7500 | H23: =IF(G23=0,"-",D23/G23-1) -> -1
A24: Program / Service Fees | B24: Earned Revenue | C24: 25000 | E24: =C24-D24 -> 25000 | F24: =IF(SUM(D9:D30)=0,"-",D24/SUM(D9:D30)) -> - | G24: 22000 | H24: =IF(G24=0,"-",D24/G24-1) -> -1
A25: Investment Income | B25: Other | C25: 3000 | E25: =C25-D25 -> 3000 | F25: =IF(SUM(D9:D30)=0,"-",D25/SUM(D9:D30)) -> - | G25: 2800 | H25: =IF(G25=0,"-",D25/G25-1) -> -1
A26: In-Kind Donations | B26: Other | C26: 5000 | E26: =C26-D26 -> 5000 | F26: =IF(SUM(D9:D30)=0,"-",D26/SUM(D9:D30)) -> - | G26: 4500 | H26: =IF(G26=0,"-",D26/G26-1) -> -1
A27: TOTAL | C27: =SUM(C9:C26) -> 568000 | D27: =SUM(D9:D26) -> 0 | E27: =C27-D27 -> 568000 | F27: =IF(D27=0,"-",1) -> - | G27: =SUM(G9:G26) -> 480800 | H27: =IF(G27=0,"-",D27/G27-1) -> -1

Sheet Appeal Performance
A1: 📬 APPEAL PERFORMANCE TRACKER
A2: Measure the effectiveness of every fundraising appeal — mail, email, digital, events, and more.
A3: Track each appeal from launch through close. Response Rate = # Gifts / # Solicited. ROI = Revenue / Cost. Cost per Dollar Raised = Cost / Revenue.
A5: APPEAL SUMMARY TOTALS
A6: Total Solicitations Sent | B6: Total Gifts Received | C6: Overall Response Rate | D6: Total Revenue Raised ($) | E6: Total Cost ($) | F6: Overall ROI | G6: Cost per $ Raised
A7: =SUM(D9:D50) -> 9847 | B7: =SUM(E9:E50) -> 1103 | C7: =IF(A7=0,"-",B7/A7) -> 0.11201381 | D7: =SUM(F9:F50) -> 277980 | E7: =SUM(G9:G50) -> 29980 | F7: =IF(E7=0,"-",D7/E7) -> 9.2721815 | G7: =IF(D7=0,"-",E7/D7) -> 0.10784949
A8: Appeal Name | B8: Channel | C8: Launch Date | D8: # Solicited | E8: # Gifts | F8: Revenue ($) | G8: Cost ($) | H8: Response Rate | I8: Avg Gift ($) | J8: ROI | K8: Notes
A9: Year-End Mail Appeal | B9: Direct Mail | C9: 2025-11-01 | D9: 2500 | E9: 188 | F9: 28200 | G9: 3750 | H9: =IF(D9=0,"-",E9/D9) -> 0.0752 | I9: =IF(E9=0,"-",F9/E9) -> 150 | J9: =IF(G9=0,"-",F9/G9) -> 7.52 | K9: Fall Solicitation
A10: Spring Email Campaign | B10: Email | C10: 2025-03-15 | D10: 4800 | E10: 192 | F10: 14400 | G10: 480 | H10: =IF(D10=0,"-",E10/D10) -> 0.04 | I10: =IF(E10=0,"-",F10/E10) -> 75 | J10: =IF(G10=0,"-",F10/G10) -> 30 | K10: 3-email series
A11: GivingTuesday Online | B11: Digital | C11: 2025-12-03 | D11: 0 | E11: 142 | F11: 9940 | G11: 250 | H11: =IF(D11=0,"-",E11/D11) -> - | I11: =IF(E11=0,"-",F11/E11) -> 70 | J11: =IF(G11=0,"-",F11/G11) -> 39.76 | K11: Peer-to-peer + social media
A12: Annual Gala | B12: Event | C12: 2025-10-15 | D12: 350 | E12: 312 | F12: 45000 | G12: 12000 | H12: =IF(D12=0,"-",E12/D12) -> 0.89142857 | I12: =IF(E12=0,"-",F12/E12) -> 144.23077 | J12: =IF(G12=0,"-",F12/G12) -> 3.75 | K12: Net revenue after costs
A13: Golf Tournament | B13: Event | C13: 2025-06-10 | D13: 144 | E13: 144 | F13: 22000 | G13: 8500 | H13: =IF(D13=0,"-",E13/D13) -> 1 | I13: =IF(E13=0,"-",F13/E13) -> 152.77778 | J13: =IF(G13=0,"-",F13/G13) -> 2.5882353 | K13: Sponsorship + registrations
A14: Major Gift Solicitations | B14: Personal Ask | C14: 2025-01-01 | D14: 45 | E14: 32 | F14: 85000 | G14: 2500 | H14: =IF(D14=0,"-",E14/D14) -> 0.71111111 | I14: =IF(E14=0,"-",F14/E14) -> 2656.25 | J14: =IF(G14=0,"-",F14/G14) -> 34 | K14: CEO + Board outreach
A15: Monthly Giving Acquisition | B15: Digital | C15: 2025-04-01 | D15: 1200 | E15: 48 | F15: 8640 | G15: 600 | H15: =IF(D15=0,"-",E15/D15) -> 0.04 | I15: =IF(E15=0,"-",F15/E15) -> 180 | J15: =IF(G15=0,"-",F15/G15) -> 14.4 | K15: 12-month projected value
A16: Foundation Grant Proposals | B16: Grants | C16: 2025-02-01 | D16: 8 | E16: 5 | F16: 60000 | G16: 1500 | H16: =IF(D16=0,"-",E16/D16) -> 0.625 | I16: =IF(E16=0,"-",F16/E16) -> 12000 | J16: =IF(G16=0,"-",F16/G16) -> 40 | K16: Includes research time
A17: Summer Lapsed Donor Reactivation | B17: Email | C17: 2025-07-01 | D17: 800 | E17: 40 | F17: 4800 | G17: 400 | H17: =IF(D17=0,"-",E17/D17) -> 0.05 | I17: =IF(E17=0,"-",F17/E17) -> 120 | J17: =IF(G17=0,"-",F17/G17) -> 12 | K17: LYBUNT outreach

Sheet Monthly Progress
A1: 📈 MONTHLY FUNDRAISING PROGRESS TRACKER
A2: Track revenue month-by-month against your annual goal. Cumulative totals update automatically.
A3: Enter actual revenue in column C each month. Projections, cumulative totals, and % of goal auto-calculate.
A5: ANNUAL GOAL SETTINGS
A6: Annual Revenue Goal ($):
A7: Monthly Average Needed ($): | D7: =IF(D6=0,"-",D6/12) -> -
A8: YTD Actual ($): | D8: =SUM(C18:C29) -> 0
A9: YTD Goal Pace ($): | D9: =IF(D6=0,"-",D6/12*COUNTA(C18:C29)) -> -
A10: Ahead / Behind ($): | D10: =IF(D6=0,"-",D8-D9) -> -
A12: MONTHLY REVENUE LOG
A13: Tip: Enter each revenue source separately or combined by month — whatever matches your reporting.
A17: Month | B17: Month Goal ($) | C17: Total Actual ($) | D17: Major Gifts ($) | E17: Annual Fund ($) | F17: Grants ($) | G17: Events ($) | H17: Online ($) | I17: Cumulative ($) | J17: % of Annual Goal
A18: July | B18: =IF(D6=0,"-",D6/12) -> - | C18: =IF(D18+E18+F18+G18+H18=0,"",D18+E18+F18+G18+H18) | I18: =SUM($C$18:C18) -> 0 | J18: =IF(D6=0,"-",I18/D6) -> -
A19: August | B19: =IF(D6=0,"-",D6/12) -> - | C19: =IF(D19+E19+F19+G19+H19=0,"",D19+E19+F19+G19+H19) | I19: =SUM($C$18:C19) -> 0 | J19: =IF(D6=0,"-",I19/D6) -> -
A20: September | B20: =IF(D6=0,"-",D6/12) -> - | C20: =IF(D20+E20+F20+G20+H20=0,"",D20+E20+F20+G20+H20) | I20: =SUM($C$18:C20) -> 0 | J20: =IF(D6=0,"-",I20/D6) -> -
A21: October | B21: =IF(D6=0,"-",D6/12) -> - | C21: =IF(D21+E21+F21+G21+H21=0,"",D21+E21+F21+G21+H21) | I21: =SUM($C$18:C21) -> 0 | J21: =IF(D6=0,"-",I21/D6) -> -
A22: November | B22: =IF(D6=0,"-",D6/12) -> - | C22: =IF(D22+E22+F22+G22+H22=0,"",D22+E22+F22+G22+H22) | I22: =SUM($C$18:C22) -> 0 | J22: =IF(D6=0,"-",I22/D6) -> -
A23: December | B23: =IF(D6=0,"-",D6/12) -> - | C23: =IF(D23+E23+F23+G23+H23=0,"",D23+E23+F23+G23+H23) | I23: =SUM($C$18:C23) -> 0 | J23: =IF(D6=0,"-",I23/D6) -> -
A24: January | B24: =IF(D6=0,"-",D6/12) -> - | C24: =IF(D24+E24+F24+G24+H24=0,"",D24+E24+F24+G24+H24) | I24: =SUM($C$18:C24) -> 0 | J24: =IF(D6=0,"-",I24/D6) -> -
A25: February | B25: =IF(D6=0,"-",D6/12) -> - | C25: =IF(D25+E25+F25+G25+H25=0,"",D25+E25+F25+G25+H25) | I25: =SUM($C$18:C25) -> 0 | J25: =IF(D6=0,"-",I25/D6) -> -
A26: March | B26: =IF(D6=0,"-",D6/12) -> - | C26: =IF(D26+E26+F26+G26+H26=0,"",D26+E26+F26+G26+H26) | I26: =SUM($C$18:C26) -> 0 | J26: =IF(D6=0,"-",I26/D6) -> -
A27: April | B27: =IF(D6=0,"-",D6/12) -> - | C27: =IF(D27+E27+F27+G27+H27=0,"",D27+E27+F27+G27+H27) | I27: =SUM($C$18:C27) -> 0 | J27: =IF(D6=0,"-",I27/D6) -> -
A28: May | B28: =IF(D6=0,"-",D6/12) -> - | C28: =IF(D28+E28+F28+G28+H28=0,"",D28+E28+F28+G28+H28) | I28: =SUM($C$18:C28) -> 0 | J28: =IF(D6=0,"-",I28/D6) -> -
A29: June | B29: =IF(D6=0,"-",D6/12) -> - | C29: =IF(D29+E29+F29+G29+H29=0,"",D29+E29+F29+G29+H29) | I29: =SUM($C$18:C29) -> 0 | J29: =IF(D6=0,"-",I29/D6) -> -
A30: ANNUAL TOTAL | B30: =IF(D6=0,"-",D6) -> - | C30: =SUM(C18:C29) -> 0 | D30: =SUM(D18:D29) -> 0 | E30: =SUM(E18:E29) -> 0 | F30: =SUM(F18:F29) -> 0 | G30: =SUM(G18:G29) -> 0 | H30: =SUM(H18:H29) -> 0 | J30: =IF(D6=0,"-",C30/D6) -> -

Sheet Donor Pyramid
A1: 🔺 DONOR PYRAMID ANALYSIS
A2: Understand your donor base by gift tier. Identify upgrade potential and pipeline gaps.
A3: Enter actual donor counts and revenue in columns D and E. Benchmarks and upgrade targets auto-calculate.
A5: PYRAMID SUMMARY
A6: Total Donors | B6: Total Revenue ($) | C6: Major Gift % of Rev | D6: Mid-Level % of Rev | E6: Avg Gift Size ($) | F6: Upgrade Opportunities
A7: =SUM(C9:C19) -> 0 | B7: =SUM(E9:E19) -> 0 | C7: =IF(B7=0,"-",SUMIF(A9:A19,"Major Donor",E9:E19)/B7) -> - | D7: =IF(B7=0,"-",SUMIF(A9:A19,"Mid-Level",E9:E19)/B7) -> - | E7: =IF(A7=0,"-",B7/A7) -> - | F7: =SUMIF(H9:H19,">0",H9:H19) -> 0
A8: Tier | B8: Gift Range | C8: # Donors (Actual) | D8: # Donors (Goal) | E8: Revenue ($) | F8: % of Total Rev | G8: Avg Gift ($) | H8: Upgrade Target | I8: Notes
A9: Principal Donor | B9: $50,000+ | D9: 2 | F9: =IF(SUM(E9:E20)=0,"-",E9/SUM(E9:E20)) -> - | G9: =IF(C9=0,"-",E9/C9) -> - | H9: =IF(C9=0,"-",D9-C9) -> -
A10: Major Donor | B10: $10,000–$49,999 | D10: 5 | F10: =IF(SUM(E9:E20)=0,"-",E10/SUM(E9:E20)) -> - | G10: =IF(C10=0,"-",E10/C10) -> - | H10: =IF(C10=0,"-",D10-C10) -> -
A11: Leadership Donor | B11: $5,000–$9,999 | D11: 8 | F11: =IF(SUM(E9:E20)=0,"-",E11/SUM(E9:E20)) -> - | G11: =IF(C11=0,"-",E11/C11) -> - | H11: =IF(C11=0,"-",D11-C11) -> -
A12: Mid-Level | B12: $1,000–$4,999 | D12: 25 | F12: =IF(SUM(E9:E20)=0,"-",E12/SUM(E9:E20)) -> - | G12: =IF(C12=0,"-",E12/C12) -> - | H12: =IF(C12=0,"-",D12-C12) -> -
A13: Mid-Level | B13: $500–$999 | D13: 40 | F13: =IF(SUM(E9:E20)=0,"-",E13/SUM(E9:E20)) -> - | G13: =IF(C13=0,"-",E13/C13) -> - | H13: =IF(C13=0,"-",D13-C13) -> -
A14: General | B14: $250–$499 | D14: 75 | F14: =IF(SUM(E9:E20)=0,"-",E14/SUM(E9:E20)) -> - | G14: =IF(C14=0,"-",E14/C14) -> - | H14: =IF(C14=0,"-",D14-C14) -> -
A15: General | B15: $100–$249 | D15: 150 | F15: =IF(SUM(E9:E20)=0,"-",E15/SUM(E9:E20)) -> - | G15: =IF(C15=0,"-",E15/C15) -> - | H15: =IF(C15=0,"-",D15-C15) -> -
A16: General | B16: $50–$99 | D16: 200 | F16: =IF(SUM(E9:E20)=0,"-",E16/SUM(E9:E20)) -> - | G16: =IF(C16=0,"-",E16/C16) -> - | H16: =IF(C16=0,"-",D16-C16) -> -
A17: General | B17: $1–$49 | D17: 300 | F17: =IF(SUM(E9:E20)=0,"-",E17/SUM(E9:E20)) -> - | G17: =IF(C17=0,"-",E17/C17) -> - | H17: =IF(C17=0,"-",D17-C17) -> -
A18: First-Time | B18: Any Amount | D18: 50 | F18: =IF(SUM(E9:E20)=0,"-",E18/SUM(E9:E20)) -> - | G18: =IF(C18=0,"-",E18/C18) -> - | H18: =IF(C18=0,"-",D18-C18) -> -
A19: Lapsed | B19: No gift this yr | D19: 0 | F19: =IF(SUM(E9:E20)=0,"-",E19/SUM(E9:E20)) -> - | G19: =IF(C19=0,"-",E19/C19) -> - | H19: =IF(C19=0,"-",D19-C19) -> -
A20: TOTAL | C20: =SUM(C9:C19) -> 0 | D20: =SUM(D9:D19) -> 855 | E20: =SUM(E9:E19) -> 0 | F20: 100%

Sheet KPI Benchmarks
A1: 🏅 FUNDRAISING KPI BENCHMARKS & GOAL-SETTING
A2: Compare your metrics to industry standards. Set improvement targets and track progress.
A3: Industry benchmarks are based on AFP, Fundraising Effectiveness Project, and Blackbaud data. Enter your actuals in column D and goals in column F.
A5: KEY PERFORMANCE INDICATORS — INDUSTRY BENCHMARKS
A6: KPI | B6: Category | C6: Industry Low | D6: Industry Avg | E6: Industry High | F6: Your Actual | G6: Your Goal | H6: Status
A7: Overall Donor Retention Rate | B7: Retention | C7: 40% | D7: 45% | E7: 55% | H7: =IF(F7="","—",IF(F7=G7,"✅ On Target",IF(F7>G7,"🔼 Above Goal","🔽 Below Goal"))) -> —
A8: New Donor Retention Rate | B8: Retention | C8: 18% | D8: 23% | E8: 30% | H8: =IF(F8="","—",IF(F8=G8,"✅ On Target",IF(F8>G8,"🔼 Above Goal","🔽 Below Goal"))) -> —
A9: Major Donor Retention Rate | B9: Retention | C9: 75% | D9: 85% | E9: 95% | H9: =IF(F9="","—",IF(F9=G9,"✅ On Target",IF(F9>G9,"🔼 Above Goal","🔽 Below Goal"))) -> —
A10: Donor Upgrade Rate | B10: Retention | C10: 10% | D10: 15% | E10: 25% | H10: =IF(F10="","—",IF(F10=G10,"✅ On Target",IF(F10>G10,"🔼 Above Goal","🔽 Below Goal"))) -> —
A11: Average Gift Size (All Donors) | B11: Gift Metrics | C11: $75 | D11: $150 | E11: $300 | H11: =IF(F11="","—",IF(F11=G11,"✅ On Target",IF(F11>G11,"🔼 Above Goal","🔽 Below Goal"))) -> —
A12: Average Major Gift Size | B12: Gift Metrics | C12: $10K | D12: $25K | E12: $100K+ | H12: =IF(F12="","—",IF(F12=G12,"✅ On Target",IF(F12>G12,"🔼 Above Goal","🔽 Below Goal"))) -> —
A13: Median Gift Size | B13: Gift Metrics | C13: $50 | D13: $100 | E13: $200 | H13: =IF(F13="","—",IF(F13=G13,"✅ On Target",IF(F13>G13,"🔼 Above Goal","🔽 Below Goal"))) -> —
A14: Cost to Raise $1 (Overall) | B14: Efficiency | C14: $0.30 | D14: $0.20 | E14: $0.10 | H14: =IF(F14="","—",IF(F14=G14,"✅ On Target",IF(F14>G14,"🔼 Above Goal","🔽 Below Goal"))) -> —
A15: Cost per New Donor Acquired | B15: Efficiency | C15: $75 | D15: $50 | E15: $25 | H15: =IF(F15="","—",IF(F15=G15,"✅ On Target",IF(F15>G15,"🔼 Above Goal","🔽 Below Goal"))) -> —
A16: Direct Mail Response Rate | B16: Appeals | C16: 0.5% | D16: 1.0% | E16: 2.5% | H16: =IF(F16="","—",IF(F16=G16,"✅ On Target",IF(F16>G16,"🔼 Above Goal","🔽 Below Goal"))) -> —
A17: Email Appeal Response Rate | B17: Appeals | C17: 0.5% | D17: 1.5% | E17: 3.0% | H17: =IF(F17="","—",IF(F17=G17,"✅ On Target",IF(F17>G17,"🔼 Above Goal","🔽 Below Goal"))) -> —
A18: Online Giving % of Total Revenue | B18: Digital | C18: 10% | D18: 20% | E18: 35% | H18: =IF(F18="","—",IF(F18=G18,"✅ On Target",IF(F18>G18,"🔼 Above Goal","🔽 Below Goal"))) -> —
... A26: Prospect-to-Donor Conversion Rate | B26: Pipeline | C26: 10% | D26: 20% | E26: 35% | H26: =IF(F26="","—",IF(F26=G26,"✅ On Target",IF(F26>G26,"🔼 Above Goal","🔽 Below Goal"))) -> —
A28: DATA SOURCES & NOTES
A29: • AFP Fundraising Effectiveness Project (FEP): Annual report on donor retention, gift sizes, and upgrade rates across 10,000+ nonprofits.
A30: • Blackbaud Institute Index: Sector-specific benchmarks for online giving, direct response, and digital fundraising.
A31: • M+R Benchmarks Study: Annual report on digital fundraising, email, mobile, and social media metrics for nonprofits.
A32: • Chronicle of Philanthropy: Annual fundraising reports and sector analysis.
A33: • Note: Benchmarks vary significantly by organization size, sector, and geography. Use as directional guides, not absolute targets.
